[{"Tag": "", "Active To": "31.12.2015", "Shelf Price": "\u20ac0.79", "id": "0", "Campaign Type": "manual", "Active From": "01.06.2014", "Additional Info": "Mars od. Twix, 120g", "Unit Goal": "", "Budget": "\u20ac100,000.00", "Status": "draft", "Revenue Goal": "", "Feature Price": "", "Description": "Danone Mix Joghurt", "Purchase Price": "", "Multibuy": "1"}, {"Tag": "", "Active To": "31.12.2015", "Shelf Price": "", "id": "1", "Campaign Type": "manual", "Active From": "01.06.2014", "Additional Info": "Einzelriegel an der Kassenauslage", "Unit Goal": "", "Budget": "\u20ac100,000.00", "Status": "draft", "Revenue Goal": "", "Feature Price": "", "Description": "Duplo Schokoriegel", "Purchase Price": "", "Multibuy": "1"}, {"Tag": "", "Active To": "17.10.2015", "Shelf Price": "\u20ac3.95", "id": "2", "Campaign Type": "manual", "Active From": "15.01.2015", "Additional Info": "Lassen Sie mich aus den Kiosk raus!", "Unit Goal": "100000000", "Budget": "\u20ac100,000.00", "Status": "draft", "Revenue Goal": "100000000", "Feature Price": "\u20ac2.77", "Description": "Magnus in Kiosk", "Purchase Price": "\u20ac1.98", "Multibuy": "1"}, {"Tag": "", "Active To": "31.12.2015", "Shelf Price": "\u20ac1.95", "id": "3", "Campaign Type": "manual", "Active From": "01.06.2014", "Additional Info": "15x10er Packung", "Unit Goal": "100000000", "Budget": "\u20ac100,000.00", "Status": "draft", "Revenue Goal": "100000000", "Feature Price": "\u20ac1.36", "Description": "Tempo Taschent\u00fccher", "Purchase Price": "\u20ac0.97", "Multibuy": "1"}, {"Tag": "Baustein-C", "Active To": "31.12.2015", "Shelf Price": "\u20ac4.99", "id": "4", "Campaign Type": "loyalty", "Active From": "18.05.2015", "Additional Info": "2x250g Packung", "Unit Goal": "", "Budget": "", "Status": "draft", "Revenue Goal": "", "Feature Price": "", "Description": "Bahlsen Selection Keks- u. Waffelmischung", "Purchase Price": "", "Multibuy": "1"}, {"Tag": "Baustein-C", "Active To": "31.12.2015", "Shelf Price": "\u20ac0.99", "id": "5", "Campaign Type": "loyalty", "Active From": "18.05.2015", "Additional Info": "500ml Fl., versch. Sorten", "Unit Goal": "", "Budget": "", "Status": "draft", "Revenue Goal": "", "Feature Price": "", "Description": "Fit Geschirrsp\u00fclmittel", "Purchase Price": "", "Multibuy": "1"}, {"Tag": "Baustein-C", "Active To": "31.12.2015", "Shelf Price": "\u20ac8.99", "id": "6", "Campaign Type": "loyalty", "Active From": "18.05.2015", "Additional Info": "0,75L Fl., Riesling, Chardonnay od. Rose", "Unit Goal": "", "Budget": "", "Status": "draft", "Revenue Goal": "", "Feature Price": "", "Description": "F\u00fcrst von Metternich Sekt", "Purchase Price": "", "Multibuy": "1"}, {"Tag": "", "Active To": "04.07.2015", "Shelf Price": "\u20ac1.99", "id": "7", "Campaign Type": "feature_promotion", "Active From": "01.07.2015", "Additional Info": "750g Packung, tiefg.", "Unit Goal": "677", "Budget": "\u20ac0.00", "Status": "draft", "Revenue Goal": "0", "Feature Price": "\u20ac1.49", "Description": "Agrarfrost Back Frites oder Knusperfrites asdas", "Purchase Price": "\u20ac1.38", "Multibuy": "10"}, {"Tag": "", "Active To": "06.07.2015", "Shelf Price": "\u20ac6.49", "id": "8", "Campaign Type": "feature_promotion", "Active From": "09.07.2015", "Additional Info": "750ml Fl.", "Unit Goal": "68", "Budget": "\u20ac0.00", "Status": "draft", "Revenue Goal": "0", "Feature Price": "\u20ac5.49", "Description": "Alba\u00f6l Schwed. Raps\u00f6l", "Purchase Price": "\u20ac4.42", "Multibuy": "10"}, {"Tag": "", "Active To": "06.07.2015", "Shelf Price": "\u20ac0.00", "id": "9", "Campaign Type": "feature_promotion", "Active From": "06.07.2015", "Additional Info": "500g Becher, versch. Sorten", "Unit Goal": "10000", "Budget": "\u20ac0.00", "Status": "draft", "Revenue Goal": "0", "Feature Price": "\u20ac0.00", "Description": "Alpro Soya Joghurt", "Purchase Price": "\u20ac0.00", "Multibuy": "1"}, {"Tag": "", "Active To": "01.07.2015", "Shelf Price": "\u20ac2.69", "id": "10", "Campaign Type": "feature_promotion", "Active From": "01.07.2015", "Additional Info": "212,5 / 225g Packung, versch. Sorten", "Unit Goal": "1590", "Budget": "\u20ac0.00", "Status": "draft", "Revenue Goal": "0", "Feature Price": "\u20ac1.99", "Description": "Amicelli Waffelr\u00f6llchen", "Purchase Price": "\u20ac1.88", "Multibuy": "5"}, {"Tag": "", "Active To": "31.12.2015", "Shelf Price": "\u20ac1.39", "id": "11", "Campaign Type": "feature_promotion", "Active From": "16.04.2015", "Additional Info": "125g Packung, versch. Sorten", "Unit Goal": "0", "Budget": "\u20ac0.00", "Status": "draft", "Revenue Goal": "0", "Feature Price": "\u20ac0.00", "Description": "Bahlsen Leibniz Choco Kekse", "Purchase Price": "\u20ac0.00", "Multibuy": "1"}, {"Tag": "Baustein-D", "Active To": "31.12.2015", "Shelf Price": "\u20ac1.79", "id": "12", "Campaign Type": "feature_promotion", "Active From": "16.04.2015", "Additional Info": "200g Packung", "Unit Goal": "", "Budget": "", "Status": "draft", "Revenue Goal": "", "Feature Price": "", "Description": "Bahlsen Leibniz Vollkorn-Kekse", "Purchase Price": "", "Multibuy": "1"}, {"Tag": "Baustein-A", "Active To": "31.12.2015", "Shelf Price": "\u20ac2.49", "id": "13", "Campaign Type": "feature_promotion", "Active From": "15.04.2015", "Additional Info": "300g Packung, versch. Sorten", "Unit Goal": "134", "Budget": "", "Status": "draft", "Revenue Goal": "", "Feature Price": "\u20ac2.29", "Description": "Barilla Fertiggerichte", "Purchase Price": "\u20ac2.16", "Multibuy": "10"}, {"Tag": "", "Active To": "17.05.2015", "Shelf Price": "\u20ac1.59", "id": "14", "Campaign Type": "feature_promotion", "Active From": "01.04.2015", "Additional Info": "jede 500g Packung", "Unit Goal": "10000", "Budget": "", "Status": "draft", "Revenue Goal": "", "Feature Price": "", "Description": "Barilla Nudeln", "Purchase Price": "\u20ac0.80", "Multibuy": "1"}, {"Tag": "", "Active To": "17.05.2015", "Shelf Price": "\u20ac3.29", "id": "15", "Campaign Type": "feature_promotion", "Active From": "01.04.2015", "Additional Info": "190g od. 200g Glas, versch. Sorten", "Unit Goal": "10000", "Budget": "", "Status": "draft", "Revenue Goal": "", "Feature Price": "", "Description": "Barilla Pesto Saucen", "Purchase Price": "\u20ac1.65", "Multibuy": "1"}, {"Tag": "", "Active To": "17.05.2015", "Shelf Price": "\u20ac0.75", "id": "16", "Campaign Type": "feature_promotion", "Active From": "01.04.2015", "Additional Info": "200g Becher", "Unit Goal": "10000", "Budget": "", "Status": "draft", "Revenue Goal": "", "Feature Price": "", "Description": "Bayernland Kerniger Frischk\u00e4se", "Purchase Price": "\u20ac0.40", "Multibuy": "1"}, {"Tag": "Baustein-A", "Active To": "31.12.2015", "Shelf Price": "\u20ac3.49", "id": "17", "Campaign Type": "feature_promotion", "Active From": "25.05.2015", "Additional Info": "6 x 0,33L Fl.", "Unit Goal": "656", "Budget": "", "Status": "draft", "Revenue Goal": "", "Feature Price": "\u20ac2.99", "Description": "Berliner Kindl Jubil\u00e4ums Pilsener", "Purchase Price": "\u20ac2.92", "Multibuy": "10"}, {"Tag": "Baustein-A", "Active To": "31.12.2015", "Shelf Price": "\u20ac4.49", "id": "18", "Campaign Type": "feature_promotion", "Active From": "15.04.2015", "Additional Info": "6x 0,33L. Fl., versch. Sorten", "Unit Goal": "543", "Budget": "", "Status": "draft", "Revenue Goal": "", "Feature Price": "\u20ac3.99", "Description": "Berliner Kindl Weisse", "Purchase Price": "\u20ac3.99", "Multibuy": "10"}, {"Tag": "Baustein-A", "Active To": "21.06.2015", "Shelf Price": "\u20ac1.29", "id": "19", "Campaign Type": "feature_promotion", "Active From": "25.05.2015", "Additional Info": "150g Packung", "Unit Goal": "1000", "Budget": "", "Status": "draft", "Revenue Goal": "", "Feature Price": "\u20ac1.19", "Description": "Birkenhof Delikatess Gutsleberwurst", "Purchase Price": "\u20ac0.60", "Multibuy": "3"}, {"Tag": "Baustein-A", "Active To": "31.12.2015", "Shelf Price": "\u20ac2.59", "id": "20", "Campaign Type": "feature_promotion", "Active From": "25.05.2015", "Additional Info": "370g Glas, versch. Sorten", "Unit Goal": "2158", "Budget": "", "Status": "draft", "Revenue Goal": "", "Feature Price": "\u20ac1.99", "Description": "Bonne Maman Konfit\u00fcre o. Gelee", "Purchase Price": "\u20ac1.70", "Multibuy": "10"}, {"Tag": "", "Active To": "17.05.2015", "Shelf Price": "", "id": "21", "Campaign Type": "feature_promotion", "Active From": "01.04.2015", "Additional Info": "225g Packung", "Unit Goal": "10000", "Budget": "", "Status": "draft", "Revenue Goal": "", "Feature Price": "", "Description": "Brandt Zwieback", "Purchase Price": "", "Multibuy": "1"}, {"Tag": "", "Active To": "17.05.2015", "Shelf Price": "\u20ac1.59", "id": "22", "Campaign Type": "feature_promotion", "Active From": "01.04.2015", "Additional Info": "Tiefk\u00fchl-Br\u00f6tchen, versch. Sorten", "Unit Goal": "10000", "Budget": "", "Status": "draft", "Revenue Goal": "", "Feature Price": "", "Description": "C&W Unsere Goldst\u00fccke", "Purchase Price": "\u20ac0.80", "Multibuy": "1"}, {"Tag": "Baustein-A", "Active To": "31.12.2015", "Shelf Price": "\u20ac2.69", "id": "23", "Campaign Type": "feature_promotion", "Active From": "15.04.2015", "Additional Info": "190g Packung", "Unit Goal": "5197", "Budget": "", "Status": "draft", "Revenue Goal": "", "Feature Price": "\u20ac1.99", "Description": "Celebrations, Milchschokol. Mischung", "Purchase Price": "\u20ac2.03", "Multibuy": "10"}, {"Tag": "", "Active To": "17.05.2015", "Shelf Price": "\u20ac1.99", "id": "24", "Campaign Type": "feature_promotion", "Active From": "01.04.2015", "Additional Info": "Alle 175g Packungen, versch. Sorten", "Unit Goal": "10000", "Budget": "", "Status": "draft", "Revenue Goal": "", "Feature Price": "", "Description": "Chio Chips", "Purchase Price": "\u20ac1.00", "Multibuy": "1"}, {"Tag": "Baustein-A", "Active To": "31.12.2015", "Shelf Price": "", "id": "25", "Campaign Type": "feature_promotion", "Active From": "15.04.2015", "Additional Info": "750ml - 2L Flasche", "Unit Goal": "116", "Budget": "", "Status": "draft", "Revenue Goal": "", "Feature Price": "\u20ac2.99", "Description": "Cillit Bang Reiniger", "Purchase Price": "\u20ac2.69", "Multibuy": "10"}, {"Tag": "", "Active To": "30.11.-0001", "Shelf Price": "\u20ac1.09", "id": "26", "Campaign Type": "feature_promotion", "Active From": "30.11.-0001", "Additional Info": "Alle 1L Flaschen, versch. Sorten", "Unit Goal": "10000", "Budget": "", "Status": "draft", "Revenue Goal": "", "Feature Price": "", "Description": "Coca-Cola od. Fanta", "Purchase Price": "\u20ac0.55", "Multibuy": "1"}, {"Tag": "Baustein-A", "Active To": "31.12.2015", "Shelf Price": "\u20ac1.99", "id": "27", "Campaign Type": "feature_promotion", "Active From": "15.04.2015", "Additional Info": "Alle 75ml Tuben", "Unit Goal": "997", "Budget": "", "Status": "draft", "Revenue Goal": "", "Feature Price": "\u20ac1.49", "Description": "Colgate Total Zahncreme", "Purchase Price": "\u20ac1.56", "Multibuy": "10"}, {"Tag": "", "Active To": "17.05.2015", "Shelf Price": "\u20ac1.49", "id": "28", "Campaign Type": "feature_promotion", "Active From": "01.04.2015", "Additional Info": "Alle 75ml Tuben", "Unit Goal": "10000", "Budget": "", "Status": "draft", "Revenue Goal": "", "Feature Price": "", "Description": "Colgate Zahnpasta", "Purchase Price": "\u20ac0.75", "Multibuy": "1"}, {"Tag": "", "Active To": "17.05.2015", "Shelf Price": "\u20ac1.69", "id": "29", "Campaign Type": "feature_promotion", "Active From": "01.04.2015", "Additional Info": "alle 4er, 5er und 6er Packungen", "Unit Goal": "10000", "Budget": "", "Status": "draft", "Revenue Goal": "", "Feature Price": "", "Description": "Corny M\u00fcsliriegel od. Milchsandwich", "Purchase Price": "\u20ac0.85", "Multibuy": "1"}, {"Tag": "Baustein-A", "Active To": "30.11.-0001", "Shelf Price": "\u20ac1.89", "id": "30", "Campaign Type": "feature_promotion", "Active From": "30.11.-0001", "Additional Info": "42er Packung, versch. Sorten", "Unit Goal": "405", "Budget": "", "Status": "draft", "Revenue Goal": "", "Feature Price": "\u20ac1.49", "Description": "Cottonelle feuchte Toilettent\u00fccher", "Purchase Price": "\u20ac1.17", "Multibuy": "10"}, {"Tag": "Baustein-A", "Active To": "31.12.2015", "Shelf Price": "\u20ac1.78", "id": "31", "Campaign Type": "feature_promotion", "Active From": "15.04.2015", "Additional Info": "1,5L Fl., versch. Sorten", "Unit Goal": "951", "Budget": "", "Status": "draft", "Revenue Goal": "", "Feature Price": "\u20ac1.99", "Description": "DanKlorix Hygiene-Reiniger", "Purchase Price": "\u20ac1.78", "Multibuy": "10"}, {"Tag": "", "Active To": "17.05.2015", "Shelf Price": "\u20ac1.59", "id": "32", "Campaign Type": "feature_promotion", "Active From": "01.04.2015", "Additional Info": "4x100g Packung", "Unit Goal": "10000", "Budget": "", "Status": "draft", "Revenue Goal": "", "Feature Price": "", "Description": "Danone Actimel Drink", "Purchase Price": "\u20ac0.80", "Multibuy": "1"}, {"Tag": "", "Active To": "17.05.2015", "Shelf Price": "\u20ac1.99", "id": "33", "Campaign Type": "feature_promotion", "Active From": "01.04.2015", "Additional Info": "4x125g Becher", "Unit Goal": "10000", "Budget": "", "Status": "draft", "Revenue Goal": "", "Feature Price": "", "Description": "Danone Activia", "Purchase Price": "\u20ac1.00", "Multibuy": "1"}, {"Tag": "", "Active To": "17.05.2015", "Shelf Price": "\u20ac1.59", "id": "34", "Campaign Type": "feature_promotion", "Active From": "01.04.2015", "Additional Info": "4x115g, versch. Sorten", "Unit Goal": "10000", "Budget": "", "Status": "draft", "Revenue Goal": "", "Feature Price": "", "Description": "Dany Sahne Pudding", "Purchase Price": "\u20ac0.80", "Multibuy": "1"}, {"Tag": "Baustein-D", "Active To": "31.12.2015", "Shelf Price": "\u20ac1.69", "id": "35", "Campaign Type": "feature_promotion", "Active From": "16.04.2015", "Additional Info": "400g Packung", "Unit Goal": "", "Budget": "", "Status": "draft", "Revenue Goal": "", "Feature Price": "", "Description": "De Beukelaer Prinzenrolle Kekse", "Purchase Price": "", "Multibuy": "1"}, {"Tag": "", "Active To": "17.05.2015", "Shelf Price": "\u20ac1.79", "id": "36", "Campaign Type": "feature_promotion", "Active From": "01.04.2015", "Additional Info": "4 x 125 g Packung", "Unit Goal": "10000", "Budget": "", "Status": "draft", "Revenue Goal": "", "Feature Price": "", "Description": "Dr. Oetker Paula Pudding", "Purchase Price": "\u20ac0.90", "Multibuy": "1"}, {"Tag": "", "Active To": "31.12.2015", "Shelf Price": "\u20ac2.69", "id": "37", "Campaign Type": "feature_promotion", "Active From": "01.04.2015", "Additional Info": "Einzelpackung, alle Sorten", "Unit Goal": "10000", "Budget": "", "Status": "draft", "Revenue Goal": "", "Feature Price": "", "Description": "Dr. Oetker Ristorante Pizza", "Purchase Price": "\u20ac1.35", "Multibuy": "1"}, {"Tag": "Baustein-A", "Active To": "14.06.2015", "Shelf Price": "\u20ac1.19", "id": "38", "Campaign Type": "feature_promotion", "Active From": "16.05.2015", "Additional Info": "Pulver, 92-190g Beutel, versch. Sorten", "Unit Goal": "911", "Budget": "", "Status": "draft", "Revenue Goal": "", "Feature Price": "\u20ac0.99", "Description": "Dr. Oetker s\u00fc\u00dfe Mahlzeit", "Purchase Price": "\u20ac0.78", "Multibuy": "10"}, {"Tag": "Baustein-A", "Active To": "31.12.2015", "Shelf Price": "\u20ac2.99", "id": "39", "Campaign Type": "feature_promotion", "Active From": "25.05.2015", "Additional Info": "Alle Einzelverpackungen, versch. Sorten", "Unit Goal": "4528", "Budget": "", "Status": "draft", "Revenue Goal": "", "Feature Price": "\u20ac2.22", "Description": "Dr. Oetker Tradizionale Pizza", "Purchase Price": "\u20ac1.93", "Multibuy": "10"}, {"Tag": "", "Active To": "17.05.2015", "Shelf Price": "\u20ac0.55", "id": "40", "Campaign Type": "feature_promotion", "Active From": "01.04.2015", "Additional Info": "150g, versch. Sorten", "Unit Goal": "10000", "Budget": "", "Status": "draft", "Revenue Goal": "", "Feature Price": "", "Description": "Ehrmann Almighurt", "Purchase Price": "\u20ac0.30", "Multibuy": "1"}, {"Tag": "", "Active To": "17.05.2015", "Shelf Price": "\u20ac0.69", "id": "41", "Campaign Type": "feature_promotion", "Active From": "01.04.2015", "Additional Info": "Alle 200g Packungen", "Unit Goal": "10000", "Budget": "", "Status": "draft", "Revenue Goal": "", "Feature Price": "", "Description": "Ehrmann Grand Dessert", "Purchase Price": "\u20ac0.35", "Multibuy": "1"}, {"Tag": "", "Active To": "31.12.2015", "Shelf Price": "", "id": "42", "Campaign Type": "feature_promotion", "Active From": "01.04.2015", "Additional Info": "1 x 100g Schale, versch. Sorten", "Unit Goal": "10000", "Budget": "", "Status": "draft", "Revenue Goal": "", "Feature Price": "", "Description": "Felix Katzenfutter Nass", "Purchase Price": "", "Multibuy": "1"}, {"Tag": "So1 Test", "Active To": "12.05.2015", "Shelf Price": "", "id": "43", "Campaign Type": "feature_promotion", "Active From": "07.05.2015", "Additional Info": "1 x 100g Schale, versch. Sorten", "Unit Goal": "100", "Budget": "", "Status": "draft", "Revenue Goal": "", "Feature Price": "", "Description": "Felix Katzenfutter Nass", "Purchase Price": "\u20ac0.30", "Multibuy": "3"}, {"Tag": "So1 Test", "Active To": "12.05.2015", "Shelf Price": "", "id": "44", "Campaign Type": "feature_promotion", "Active From": "07.05.2015", "Additional Info": "100g Schale, versch. Sorten", "Unit Goal": "100", "Budget": "", "Status": "draft", "Revenue Goal": "", "Feature Price": "", "Description": "Felix Katzenfutter Nass", "Purchase Price": "\u20ac0.30", "Multibuy": "3"}, {"Tag": "Baustein-A", "Active To": "31.12.2015", "Shelf Price": "\u20ac0.99", "id": "45", "Campaign Type": "feature_promotion", "Active From": "25.05.2015", "Additional Info": "1er Packung/ 20g", "Unit Goal": "10136", "Budget": "", "Status": "draft", "Revenue Goal": "", "Feature Price": "\u20ac0.79", "Description": "Fererro Kinder Joy", "Purchase Price": "\u20ac0.72", "Multibuy": "5"}, {"Tag": "Baustein-D", "Active To": "14.06.2015", "Shelf Price": "\u20ac2.69", "id": "46", "Campaign Type": "feature_promotion", "Active From": "25.05.2015", "Additional Info": "24x12,5g-Riegel Packung", "Unit Goal": "", "Budget": "", "Status": "draft", "Revenue Goal": "", "Feature Price": "", "Description": "Ferrero Kinderschokolade", "Purchase Price": "\u20ac2.32", "Multibuy": "3"}, {"Tag": "", "Active To": "17.05.2015", "Shelf Price": "\u20ac1.29", "id": "47", "Campaign Type": "feature_promotion", "Active From": "01.04.2015", "Additional Info": "5x28g Packung", "Unit Goal": "10000", "Budget": "", "Status": "draft", "Revenue Goal": "", "Feature Price": "", "Description": "Ferrero Milchschnitte", "Purchase Price": "\u20ac0.65", "Multibuy": "1"}, {"Tag": "", "Active To": "31.12.2015", "Shelf Price": "\u20ac5.99", "id": "48", "Campaign Type": "feature_promotion", "Active From": "15.04.2015", "Additional Info": "versch. Sorten", "Unit Goal": "630", "Budget": "\u20ac0.00", "Status": "draft", "Revenue Goal": "0", "Feature Price": "\u20ac4.99", "Description": "Finish Geschirrsp\u00fclmittel", "Purchase Price": "\u20ac4.38", "Multibuy": "10"}, {"Tag": "", "Active To": "17.05.2015", "Shelf Price": "", "id": "49", "Campaign Type": "feature_promotion", "Active From": "01.04.2015", "Additional Info": "150g od. 170g, versch. Sorten", "Unit Goal": "10000", "Budget": "", "Status": "draft", "Revenue Goal": "", "Feature Price": "", "Description": "Frico Gouda", "Purchase Price": "", "Multibuy": "1"}, {"Tag": "Baustein-D", "Active To": "31.12.2015", "Shelf Price": "\u20ac2.99", "id": "50", "Campaign Type": "feature_promotion", "Active From": "25.05.2015", "Additional Info": "125g Schale", "Unit Goal": "", "Budget": "", "Status": "draft", "Revenue Goal": "", "Feature Price": "", "Description": "Frische Himbeeren", "Purchase Price": "", "Multibuy": "3"}, {"Tag": "Baustein-A", "Active To": "31.12.2015", "Shelf Price": "\u20ac4.99", "id": "51", "Campaign Type": "feature_promotion", "Active From": "15.04.2015", "Additional Info": "0,75L Fl., versch. Sorten", "Unit Goal": "3064", "Budget": "", "Status": "draft", "Revenue Goal": "", "Feature Price": "\u20ac3.77", "Description": "Gallo Family Weine", "Purchase Price": "\u20ac3.69", "Multibuy": "10"}, {"Tag": "", "Active To": "17.05.2015", "Shelf Price": "\u20ac2.29", "id": "52", "Campaign Type": "feature_promotion", "Active From": "01.04.2015", "Additional Info": "Orig. Franz. Weichk\u00e4se, 200g", "Unit Goal": "10000", "Budget": "", "Status": "draft", "Revenue Goal": "", "Feature Price": "", "Description": "Geramont Weichk\u00e4se", "Purchase Price": "\u20ac1.20", "Multibuy": "1"}, {"Tag": "", "Active To": "31.12.2015", "Shelf Price": "\u20ac0.69", "id": "53", "Campaign Type": "feature_promotion", "Active From": "01.04.2015", "Additional Info": "Alle 1L Flaschen, versch. Sorten", "Unit Goal": "10000", "Budget": "", "Status": "draft", "Revenue Goal": "", "Feature Price": "", "Description": "Gerolsteiner Mineralwasser", "Purchase Price": "\u20ac0.35", "Multibuy": "1"}, {"Tag": "", "Active To": "17.05.2015", "Shelf Price": "\u20ac1.39", "id": "54", "Campaign Type": "feature_promotion", "Active From": "01.04.2015", "Additional Info": "Alle 500g Toast Packungen", "Unit Goal": "10000", "Budget": "", "Status": "draft", "Revenue Goal": "", "Feature Price": "", "Description": "Golden Toast", "Purchase Price": "\u20ac0.70", "Multibuy": "1"}, {"Tag": "Baustein-A", "Active To": "31.12.2015", "Shelf Price": "\u20ac0.49", "id": "55", "Campaign Type": "feature_promotion", "Active From": "15.04.2015", "Additional Info": "85g Packung, nass, versch. Sorten", "Unit Goal": "11071", "Budget": "", "Status": "draft", "Revenue Goal": "", "Feature Price": "\u20ac0.45", "Description": "Gourmet Gold Katzenfutter", "Purchase Price": "\u20ac0.39", "Multibuy": "10"}, {"Tag": "Baustein-A", "Active To": "31.12.2015", "Shelf Price": "\u20ac0.99", "id": "56", "Campaign Type": "feature_promotion", "Active From": "25.05.2015", "Additional Info": "0,33L Dose", "Unit Goal": "937", "Budget": "", "Status": "draft", "Revenue Goal": "", "Feature Price": "\u20ac0.79", "Description": "Guarana Antarctica Energydrink", "Purchase Price": "\u20ac0.64", "Multibuy": "10"}, {"Tag": "", "Active To": "17.05.2015", "Shelf Price": "\u20ac1.99", "id": "57", "Campaign Type": "feature_promotion", "Active From": "01.04.2015", "Additional Info": "10 Stk. Packung", "Unit Goal": "10000", "Budget": "", "Status": "draft", "Revenue Goal": "", "Feature Price": "", "Description": "Hanuta", "Purchase Price": "\u20ac1.00", "Multibuy": "1"}, {"Tag": "", "Active To": "17.05.2015", "Shelf Price": "", "id": "58", "Campaign Type": "feature_promotion", "Active From": "01.04.2015", "Additional Info": "Alle 500g Packungen", "Unit Goal": "10000", "Budget": "", "Status": "draft", "Revenue Goal": "", "Feature Price": "", "Description": "Harry Brot", "Purchase Price": "", "Multibuy": "1"}, {"Tag": "", "Active To": "17.05.2015", "Shelf Price": "\u20ac1.79", "id": "59", "Campaign Type": "feature_promotion", "Active From": "01.04.2015", "Additional Info": "Orange u. Multivitamin versch. Sort, 1L", "Unit Goal": "10000", "Budget": "", "Status": "draft", "Revenue Goal": "", "Feature Price": "", "Description": "Hohes C Fruchts\u00e4fte", "Purchase Price": "\u20ac0.90", "Multibuy": "1"}, {"Tag": "", "Active To": "17.05.2015", "Shelf Price": "", "id": "60", "Campaign Type": "feature_promotion", "Active From": "01.04.2015", "Additional Info": "Jede 10, 12, 13 und 15 Stk.-Packung", "Unit Goal": "10000", "Budget": "", "Status": "draft", "Revenue Goal": "", "Feature Price": "", "Description": "Iglo Fischst\u00e4bchen", "Purchase Price": "", "Multibuy": "1"}, {"Tag": "Baustein-A", "Active To": "31.12.2015", "Shelf Price": "\u20ac1.99", "id": "61", "Campaign Type": "feature_promotion", "Active From": "15.04.2015", "Additional Info": "168 - 180g Packung", "Unit Goal": "497", "Budget": "", "Status": "draft", "Revenue Goal": "", "Feature Price": "\u20ac1.79", "Description": "Jacobs 3 und 2 in 1 Kaffee, Getr\u00e4nkepulver", "Purchase Price": "\u20ac1.35", "Multibuy": "10"}, {"Tag": "Baustein-A", "Active To": "31.12.2015", "Shelf Price": "\u20ac0.99", "id": "62", "Campaign Type": "feature_promotion", "Active From": "15.04.2015", "Additional Info": "150 - 200g Packung, versch. Sorten", "Unit Goal": "6783", "Budget": "", "Status": "draft", "Revenue Goal": "", "Feature Price": "\u20ac0.69", "Description": "Katjes Fruchtgummi u. Lakritz", "Purchase Price": "\u20ac0.61", "Multibuy": "10"}, {"Tag": "", "Active To": "17.05.2015", "Shelf Price": "", "id": "63", "Campaign Type": "feature_promotion", "Active From": "01.04.2015", "Additional Info": "200g, versch. Sorten", "Unit Goal": "10000", "Budget": "", "Status": "draft", "Revenue Goal": "", "Feature Price": "", "Description": "Katjes Veggie Fruchtgummies", "Purchase Price": "", "Multibuy": "1"}, {"Tag": "", "Active To": "17.05.2015", "Shelf Price": "", "id": "64", "Campaign Type": "feature_promotion", "Active From": "01.04.2015", "Additional Info": "Alle Kellogg's Cerealien, versch. Sorten u. Gr\u00f6\u00dfen", "Unit Goal": "10000", "Budget": "", "Status": "draft", "Revenue Goal": "", "Feature Price": "", "Description": "Kellogg's Cerealien", "Purchase Price": "", "Multibuy": "1"}, {"Tag": "", "Active To": "17.05.2015", "Shelf Price": "\u20ac1.79", "id": "65", "Campaign Type": "feature_promotion", "Active From": "01.04.2015", "Additional Info": "Alle 250g Packungen", "Unit Goal": "10000", "Budget": "", "Status": "draft", "Revenue Goal": "", "Feature Price": "", "Description": "Kerrygold Butter", "Purchase Price": "\u20ac0.90", "Multibuy": "1"}, {"Tag": "", "Active To": "17.05.2015", "Shelf Price": "\u20ac1.99", "id": "66", "Campaign Type": "feature_promotion", "Active From": "01.04.2015", "Additional Info": "150g Packung, versch. Sorten", "Unit Goal": "10000", "Budget": "", "Status": "draft", "Revenue Goal": "", "Feature Price": "", "Description": "Kerrygold Scheibenk\u00e4se", "Purchase Price": "\u20ac1.00", "Multibuy": "1"}, {"Tag": "", "Active To": "17.05.2015", "Shelf Price": "\u20ac2.19", "id": "67", "Campaign Type": "feature_promotion", "Active From": "01.04.2015", "Additional Info": "10er Packung, 210g", "Unit Goal": "10000", "Budget": "", "Status": "draft", "Revenue Goal": "", "Feature Price": "", "Description": "Kinderriegel", "Purchase Price": "\u20ac1.10", "Multibuy": "1"}, {"Tag": "Baustein-A", "Active To": "31.12.2015", "Shelf Price": "\u20ac1.79", "id": "68", "Campaign Type": "feature_promotion", "Active From": "15.04.2015", "Additional Info": "500ml Fl.", "Unit Goal": "258", "Budget": "", "Status": "draft", "Revenue Goal": "", "Feature Price": "\u20ac1.49", "Description": "Knorr Tomaten Ketchup", "Purchase Price": "\u20ac1.13", "Multibuy": "10"}, {"Tag": "Baustein-A", "Active To": "31.12.2015", "Shelf Price": "\u20ac1.49", "id": "69", "Campaign Type": "feature_promotion", "Active From": "15.04.2015", "Additional Info": "180g Glas", "Unit Goal": "255", "Budget": "", "Status": "draft", "Revenue Goal": "", "Feature Price": "\u20ac1.29", "Description": "K\u00fchne Cocktail Cornichons Gurken", "Purchase Price": "\u20ac0.92", "Multibuy": "10"}, {"Tag": "Baustein-A", "Active To": "14.06.2015", "Shelf Price": "\u20ac2.99", "id": "70", "Campaign Type": "feature_promotion", "Active From": "16.05.2015", "Additional Info": "200 / 250ml Flasche, versch. Sorten", "Unit Goal": "606", "Budget": "", "Status": "draft", "Revenue Goal": "", "Feature Price": "\u20ac2.49", "Description": "L'Or\u00e9al Paris Elvital Haarpflege", "Purchase Price": "\u20ac1.99", "Multibuy": "5"}, {"Tag": "", "Active To": "17.05.2015", "Shelf Price": "\u20ac0.79", "id": "71", "Campaign Type": "feature_promotion", "Active From": "01.04.2015", "Additional Info": "versch. Sorten, 150g Packung", "Unit Goal": "10000", "Budget": "", "Status": "draft", "Revenue Goal": "", "Feature Price": "", "Description": "Landliebe Milchreis", "Purchase Price": "\u20ac0.40", "Multibuy": "1"}, {"Tag": "", "Active To": "17.05.2015", "Shelf Price": "\u20ac2.19", "id": "72", "Campaign Type": "feature_promotion", "Active From": "01.04.2015", "Additional Info": "140g, Original od. Leger od. Charactere", "Unit Goal": "10000", "Budget": "", "Status": "draft", "Revenue Goal": "", "Feature Price": "", "Description": "Leerdammer Scheibenk\u00e4se", "Purchase Price": "\u20ac1.10", "Multibuy": "1"}, {"Tag": "", "Active To": "31.12.2015", "Shelf Price": "", "id": "73", "Campaign Type": "feature_promotion", "Active From": "01.04.2015", "Additional Info": "Alle 200g Packungen, versch. Sort.", "Unit Goal": "10000", "Budget": "", "Status": "draft", "Revenue Goal": "", "Feature Price": "", "Description": "Leibniz Butterkeks", "Purchase Price": "", "Multibuy": "1"}, {"Tag": "Baustein-D", "Active To": "31.12.2015", "Shelf Price": "\u20ac1.39", "id": "74", "Campaign Type": "feature_promotion", "Active From": "16.04.2015", "Additional Info": "200g Packung, versch. Sorten", "Unit Goal": "", "Budget": "", "Status": "draft", "Revenue Goal": "", "Feature Price": "", "Description": "Leibniz Butterkeks", "Purchase Price": "", "Multibuy": "1"}, {"Tag": "", "Active To": "17.05.2015", "Shelf Price": "\u20ac1.69", "id": "75", "Campaign Type": "feature_promotion", "Active From": "01.04.2015", "Additional Info": "Versch. Sorten", "Unit Goal": "10000", "Budget": "", "Status": "draft", "Revenue Goal": "", "Feature Price": "", "Description": "Lorenz Chips Naturals", "Purchase Price": "\u20ac0.85", "Multibuy": "1"}, {"Tag": "", "Active To": "17.05.2015", "Shelf Price": "\u20ac1.59", "id": "76", "Campaign Type": "feature_promotion", "Active From": "01.04.2015", "Additional Info": "Classic & Joghurt, 500g Packung", "Unit Goal": "10000", "Budget": "", "Status": "draft", "Revenue Goal": "", "Feature Price": "", "Description": "L\u00e4tta Margarine", "Purchase Price": "\u20ac0.80", "Multibuy": "1"}, {"Tag": "Baustein-A", "Active To": "14.06.2015", "Shelf Price": "\u20ac3.99", "id": "77", "Campaign Type": "feature_promotion", "Active From": "16.05.2015", "Additional Info": "300 / 400ml Spr\u00fchflasche, versch. Sorten", "Unit Goal": "274", "Budget": "", "Status": "draft", "Revenue Goal": "", "Feature Price": "\u20ac3.29", "Description": "L\u2019Or\u00e9al Paris Elnett Haarspray", "Purchase Price": "\u20ac3.23", "Multibuy": "5"}, {"Tag": "", "Active To": "17.05.2015", "Shelf Price": "\u20ac0.79", "id": "78", "Campaign Type": "feature_promotion", "Active From": "01.04.2015", "Additional Info": "Einzelriegel, 51g", "Unit Goal": "10000", "Budget": "", "Status": "draft", "Revenue Goal": "", "Feature Price": "", "Description": "Mars Schokoriegel", "Purchase Price": "\u20ac0.40", "Multibuy": "1"}, {"Tag": "Baustein-A", "Active To": "31.12.2015", "Shelf Price": "\u20ac3.19", "id": "79", "Campaign Type": "feature_promotion", "Active From": "15.04.2015", "Additional Info": "6er Packung", "Unit Goal": "843", "Budget": "", "Status": "draft", "Revenue Goal": "", "Feature Price": "\u20ac2.49", "Description": "Mars, Snickers od. Bounty Ice Cream", "Purchase Price": "\u20ac2.08", "Multibuy": "10"}, {"Tag": "", "Active To": "30.11.-0001", "Shelf Price": "\u20ac1.09", "id": "80", "Campaign Type": "feature_promotion", "Active From": "30.11.-0001", "Additional Info": "Jede 100g Tafel, versch. Sort.", "Unit Goal": "10000", "Budget": "", "Status": "draft", "Revenue Goal": "", "Feature Price": "", "Description": "Milka Schokolade", "Purchase Price": "\u20ac0.50", "Multibuy": "1"}, {"Tag": "", "Active To": "31.12.2015", "Shelf Price": "\u20ac0.59", "id": "81", "Campaign Type": "feature_promotion", "Active From": "01.04.2015", "Additional Info": "150g Becher, versch. Sorten", "Unit Goal": "10000", "Budget": "", "Status": "draft", "Revenue Goal": "", "Feature Price": "", "Description": "M\u00fcller mit der Ecke", "Purchase Price": "\u20ac0.30", "Multibuy": "1"}, {"Tag": "So1 Test", "Active To": "17.05.2015", "Shelf Price": "\u20ac0.59", "id": "82", "Campaign Type": "feature_promotion", "Active From": "07.05.2015", "Additional Info": "150g Becher, versch. Sorten", "Unit Goal": "80", "Budget": "", "Status": "draft", "Revenue Goal": "", "Feature Price": "", "Description": "M\u00fcller mit der Ecke", "Purchase Price": "\u20ac0.20", "Multibuy": "5"}, {"Tag": "Baustein-D", "Active To": "14.06.2015", "Shelf Price": "\u20ac1.99", "id": "83", "Campaign Type": "feature_promotion", "Active From": "18.05.2015", "Additional Info": "Wiegeware", "Unit Goal": "", "Budget": "", "Status": "draft", "Revenue Goal": "", "Feature Price": "", "Description": "Naturkind Bananen", "Purchase Price": "", "Multibuy": "1"}, {"Tag": "Baustein-A", "Active To": "31.12.2015", "Shelf Price": "\u20ac4.79", "id": "84", "Campaign Type": "feature_promotion", "Active From": "15.04.2015", "Additional Info": "8er/16er Packung, vesch. Sorten", "Unit Goal": "2738", "Budget": "", "Status": "draft", "Revenue Goal": "", "Feature Price": "\u20ac3.99", "Description": "Nescafe Dolce Gusto Kapseln", "Purchase Price": "\u20ac3.99", "Multibuy": "10"}, {"Tag": "Baustein-A", "Active To": "31.12.2015", "Shelf Price": "\u20ac3.29", "id": "85", "Campaign Type": "feature_promotion", "Active From": "25.05.2015", "Additional Info": "275g Dose", "Unit Goal": "564", "Budget": "", "Status": "draft", "Revenue Goal": "", "Feature Price": "\u20ac2.79", "Description": "Nescafe Frappe Eiskaffee Instantpulver", "Purchase Price": "\u20ac2.01", "Multibuy": "10"}, {"Tag": "Baustein-A", "Active To": "31.12.2015", "Shelf Price": "\u20ac2.99", "id": "86", "Campaign Type": "feature_promotion", "Active From": "15.04.2015", "Additional Info": "325-450g Packungen, versch. Sorten", "Unit Goal": "1173", "Budget": "", "Status": "draft", "Revenue Goal": "", "Feature Price": "\u20ac2.39", "Description": "Nestle Fr\u00fchst\u00fcck-Cerealien", "Purchase Price": "\u20ac1.92", "Multibuy": "10"}, {"Tag": "Baustein-A", "Active To": "31.12.2015", "Shelf Price": "\u20ac1.29", "id": "87", "Campaign Type": "feature_promotion", "Active From": "25.05.2015", "Additional Info": "200g Packung", "Unit Goal": "1456", "Budget": "", "Status": "draft", "Revenue Goal": "", "Feature Price": "\u20ac0.99", "Description": "Nippon Puffreis mit Milchschokolade", "Purchase Price": "\u20ac0.77", "Multibuy": "10"}, {"Tag": "", "Active To": "31.12.2015", "Shelf Price": "\u20ac2.49", "id": "88", "Campaign Type": "feature_promotion", "Active From": "01.04.2015", "Additional Info": "450g Glas", "Unit Goal": "10000", "Budget": "", "Status": "draft", "Revenue Goal": "", "Feature Price": "", "Description": "Nutella", "Purchase Price": "\u20ac1.25", "Multibuy": "1"}, {"Tag": "", "Active To": "31.10.2015", "Shelf Price": "\u20ac1.39", "id": "89", "Campaign Type": "feature_promotion", "Active From": "01.04.2015", "Additional Info": "Alle 175g Packungen, versch. Sorten", "Unit Goal": "10000", "Budget": "", "Status": "draft", "Revenue Goal": "", "Feature Price": "", "Description": "Philadelphia Frischk\u00e4se", "Purchase Price": "\u20ac0.70", "Multibuy": "1"}, {"Tag": "Baustein-A", "Active To": "31.12.2015", "Shelf Price": "\u20ac1.25", "id": "90", "Campaign Type": "feature_promotion", "Active From": "15.04.2015", "Additional Info": "50 / 75g Packung, versch. Sorten", "Unit Goal": "2990", "Budget": "", "Status": "draft", "Revenue Goal": "", "Feature Price": "\u20ac0.99", "Description": "Pom-B\u00e4r Kartoffel-Snack", "Purchase Price": "\u20ac0.82", "Multibuy": "10"}, {"Tag": "", "Active To": "31.12.2015", "Shelf Price": "\u20ac1.99", "id": "91", "Campaign Type": "feature_promotion", "Active From": "01.04.2015", "Additional Info": "125g, versch. Sorten", "Unit Goal": "10000", "Budget": "", "Status": "draft", "Revenue Goal": "", "Feature Price": "", "Description": "Pommersche Gutsleberwurst", "Purchase Price": "\u20ac1.00", "Multibuy": "1"}, {"Tag": "So1 Test", "Active To": "17.05.2015", "Shelf Price": "\u20ac1.99", "id": "92", "Campaign Type": "feature_promotion", "Active From": "07.05.2015", "Additional Info": "125g, versch. Sorten", "Unit Goal": "50", "Budget": "", "Status": "draft", "Revenue Goal": "", "Feature Price": "", "Description": "Pommersche Gutsleberwurst", "Purchase Price": "\u20ac1.33", "Multibuy": "1"}, {"Tag": "", "Active To": "31.12.2015", "Shelf Price": "\u20ac1.99", "id": "93", "Campaign Type": "feature_promotion", "Active From": "01.04.2015", "Additional Info": "Alle 500ml & 600ml Fl., versch. Sorten", "Unit Goal": "10000", "Budget": "", "Status": "draft", "Revenue Goal": "", "Feature Price": "", "Description": "Pril Kraftgel Sp\u00fclmittel", "Purchase Price": "\u20ac1.00", "Multibuy": "1"}, {"Tag": "", "Active To": "17.05.2015", "Shelf Price": "", "id": "94", "Campaign Type": "feature_promotion", "Active From": "01.04.2015", "Additional Info": "Versch. Sorten", "Unit Goal": "10000", "Budget": "", "Status": "draft", "Revenue Goal": "", "Feature Price": "", "Description": "Pringles Chips", "Purchase Price": "", "Multibuy": "1"}, {"Tag": "", "Active To": "17.05.2015", "Shelf Price": "\u20ac1.69", "id": "95", "Campaign Type": "feature_promotion", "Active From": "01.04.2015", "Additional Info": "Alle 400g Packungen, versch. Sort.", "Unit Goal": "10000", "Budget": "", "Status": "draft", "Revenue Goal": "", "Feature Price": "", "Description": "Prinzen Rolle", "Purchase Price": "\u20ac0.85", "Multibuy": "1"}, {"Tag": "Baustein A", "Active To": "14.06.2015", "Shelf Price": "\u20ac6.99", "id": "96", "Campaign Type": "feature_promotion", "Active From": "16.05.2015", "Additional Info": "0,75L Fl.", "Unit Goal": "669", "Budget": "\u20ac0.00", "Status": "draft", "Revenue Goal": "0", "Feature Price": "\u20ac5.99", "Description": "Prosecco Conegliano Valdobbiadene", "Purchase Price": "\u20ac4.88", "Multibuy": "10"}, {"Tag": "Baustein-A", "Active To": "31.12.2015", "Shelf Price": "\u20ac0.99", "id": "97", "Campaign Type": "feature_promotion", "Active From": "15.04.2015", "Additional Info": "250ml Fl. / 200g Becher, versch. Sorten", "Unit Goal": "1315", "Budget": "", "Status": "draft", "Revenue Goal": "", "Feature Price": "\u20ac0.79", "Description": "Rama Cremefine Sahne", "Purchase Price": "\u20ac0.67", "Multibuy": "10"}, {"Tag": "", "Active To": "17.05.2015", "Shelf Price": "\u20ac0.99", "id": "98", "Campaign Type": "feature_promotion", "Active From": "01.04.2015", "Additional Info": "100g, versch. Sorten", "Unit Goal": "10000", "Budget": "", "Status": "draft", "Revenue Goal": "", "Feature Price": "", "Description": "Ritter Sport Schokolade", "Purchase Price": "\u20ac0.50", "Multibuy": "1"}, {"Tag": "Baustein-A", "Active To": "31.12.2015", "Shelf Price": "\u20ac3.99", "id": "99", "Campaign Type": "feature_promotion", "Active From": "15.04.2015", "Additional Info": "0,75L Fl., versch. Sorten", "Unit Goal": "1846", "Budget": "", "Status": "draft", "Revenue Goal": "", "Feature Price": "\u20ac2.99", "Description": "Rotk\u00e4ppchen Weine", "Purchase Price": "\u20ac2.59", "Multibuy": "10"}, {"Tag": "", "Active To": "17.05.2015", "Shelf Price": "\u20ac2.09", "id": "100", "Campaign Type": "feature_promotion", "Active From": "01.04.2015", "Additional Info": "340g, versch. Sorten", "Unit Goal": "10000", "Budget": "", "Status": "draft", "Revenue Goal": "", "Feature Price": "", "Description": "Schwartau Extra", "Purchase Price": "\u20ac1.05", "Multibuy": "1"}, {"Tag": "", "Active To": "17.05.2015", "Shelf Price": "", "id": "101", "Campaign Type": "feature_promotion", "Active From": "01.04.2015", "Additional Info": "Alle Pckg. Trockenobst und N\u00fcsse", "Unit Goal": "10000", "Budget": "", "Status": "draft", "Revenue Goal": "", "Feature Price": "", "Description": "Seeberger", "Purchase Price": "", "Multibuy": "1"}, {"Tag": "Baustein-A", "Active To": "14.06.2015", "Shelf Price": "\u20ac12.99", "id": "102", "Campaign Type": "feature_promotion", "Active From": "16.05.2015", "Additional Info": "1kg Packung, ganze Bohnen", "Unit Goal": "245", "Budget": "", "Status": "draft", "Revenue Goal": "", "Feature Price": "\u20ac10.99", "Description": "Segafredo Espresso Casa Kaffee", "Purchase Price": "\u20ac10.78", "Multibuy": "5"}, {"Tag": "", "Active To": "31.12.2015", "Shelf Price": "\u20ac0.69", "id": "103", "Campaign Type": "feature_promotion", "Active From": "01.04.2015", "Additional Info": "1x 100g Schale, versch. Sorten", "Unit Goal": "10000", "Budget": "", "Status": "draft", "Revenue Goal": "", "Feature Price": "", "Description": "Sheba Katzenfutter Nass", "Purchase Price": "\u20ac0.35", "Multibuy": "1"}, {"Tag": "Baustein-A", "Active To": "31.12.2015", "Shelf Price": "\u20ac1.69", "id": "104", "Campaign Type": "feature_promotion", "Active From": "15.04.2015", "Additional Info": "125g Packung", "Unit Goal": "2174", "Budget": "", "Status": "draft", "Revenue Goal": "", "Feature Price": "\u20ac1.39", "Description": "Snyder's Pretzel Pieces Knabbersnack", "Purchase Price": "\u20ac1.25", "Multibuy": "10"}, {"Tag": "", "Active To": "17.05.2015", "Shelf Price": "\u20ac1.79", "id": "105", "Campaign Type": "feature_promotion", "Active From": "01.04.2015", "Additional Info": "Alle 20 Stk. Packungen", "Unit Goal": "10000", "Budget": "", "Status": "draft", "Revenue Goal": "", "Feature Price": "", "Description": "Teekanne Tee", "Purchase Price": "\u20ac0.90", "Multibuy": "1"}, {"Tag": "Baustein-A", "Active To": "21.06.2015", "Shelf Price": "\u20ac1.99", "id": "106", "Campaign Type": "feature_promotion", "Active From": "25.05.2015", "Additional Info": "125g Packung", "Unit Goal": "3000", "Budget": "", "Status": "draft", "Revenue Goal": "", "Feature Price": "\u20ac1.79", "Description": "Tulip Bacon - Scheiben", "Purchase Price": "\u20ac0.95", "Multibuy": "5"}, {"Tag": "", "Active To": "17.05.2015", "Shelf Price": "", "id": "107", "Campaign Type": "feature_promotion", "Active From": "01.04.2015", "Additional Info": "4er, 5er und 5+1 Packungen", "Unit Goal": "10000", "Budget": "", "Status": "draft", "Revenue Goal": "", "Feature Price": "", "Description": "Twix Schokoriegel", "Purchase Price": "", "Multibuy": "1"}, {"Tag": "", "Active To": "17.05.2015", "Shelf Price": "\u20ac1.99", "id": "108", "Campaign Type": "feature_promotion", "Active From": "01.04.2015", "Additional Info": "Alle 250g Packungen, versch. Sorten", "Unit Goal": "10000", "Budget": "", "Status": "draft", "Revenue Goal": "", "Feature Price": "", "Description": "Uncle Ben's Express Reis", "Purchase Price": "\u20ac1.00", "Multibuy": "1"}, {"Tag": "", "Active To": "30.11.2015", "Shelf Price": "\u20ac2.99", "id": "109", "Campaign Type": "feature_promotion", "Active From": "01.04.2015", "Additional Info": "versch. Sorten, 1L", "Unit Goal": "1000", "Budget": "", "Status": "draft", "Revenue Goal": "", "Feature Price": "", "Description": "Valensina Erntefrisch Gepresst Saft", "Purchase Price": "", "Multibuy": "1"}, {"Tag": "Baustein-A", "Active To": "31.12.2015", "Shelf Price": "\u20ac0.89", "id": "110", "Campaign Type": "feature_promotion", "Active From": "15.04.2015", "Additional Info": "1,5L Pet Fl., versch. Sorten", "Unit Goal": "1220", "Budget": "", "Status": "draft", "Revenue Goal": "", "Feature Price": "\u20ac3.49", "Description": "Vio Mineralwasser", "Purchase Price": "\u20ac3.02", "Multibuy": "10"}, {"Tag": "", "Active To": "17.05.2015", "Shelf Price": "", "id": "111", "Campaign Type": "feature_promotion", "Active From": "01.04.2015", "Additional Info": "versch. Sorten und Gr\u00f6\u00dfen", "Unit Goal": "10000", "Budget": "", "Status": "draft", "Revenue Goal": "", "Feature Price": "", "Description": "Vitalis M\u00fcsli", "Purchase Price": "", "Multibuy": "1"}, {"Tag": "", "Active To": "17.05.2015", "Shelf Price": "\u20ac1.39", "id": "112", "Campaign Type": "feature_promotion", "Active From": "01.04.2015", "Additional Info": "versch. Sorten", "Unit Goal": "10000", "Budget": "", "Status": "draft", "Revenue Goal": "", "Feature Price": "", "Description": "Wasa Kn\u00e4ckebrot", "Purchase Price": "\u20ac0.70", "Multibuy": "1"}, {"Tag": "Baustein-A", "Active To": "31.12.2015", "Shelf Price": "\u20ac0.69", "id": "113", "Campaign Type": "feature_promotion", "Active From": "25.05.2015", "Additional Info": "150g Becher, versch. Sorten", "Unit Goal": "5863", "Budget": "", "Status": "draft", "Revenue Goal": "", "Feature Price": "\u20ac0.49", "Description": "Weihenstephan Rahmjoghurt", "Purchase Price": "\u20ac0.38", "Multibuy": "10"}, {"Tag": "Baustein-A", "Active To": "31.12.2015", "Shelf Price": "\u20ac0.99", "id": "114", "Campaign Type": "feature_promotion", "Active From": "25.05.2015", "Additional Info": "400g Dose, versch. Sorten", "Unit Goal": "850", "Budget": "", "Status": "draft", "Revenue Goal": "", "Feature Price": "\u20ac0.79", "Description": "Whiskas Katzenfutter", "Purchase Price": "\u20ac0.72", "Multibuy": "10"}, {"Tag": "Baustein-A", "Active To": "31.12.2015", "Shelf Price": "\u20ac6.79", "id": "115", "Campaign Type": "feature_promotion", "Active From": "25.05.2015", "Additional Info": "0,7L Fl., 30% Vol.", "Unit Goal": "468", "Budget": "", "Status": "draft", "Revenue Goal": "", "Feature Price": "\u20ac4.99", "Description": "Wilthener Gebirgskr\u00e4uter Lik\u00f6r", "Purchase Price": "\u20ac4.99", "Multibuy": "10"}, {"Tag": "Baustein A", "Active To": "31.12.2015", "Shelf Price": "\u20ac7.99", "id": "116", "Campaign Type": "feature_promotion", "Active From": "15.04.2015", "Additional Info": "0,7L Fl., 37,5% Vol.", "Unit Goal": "1953", "Budget": "\u20ac0.00", "Status": "draft", "Revenue Goal": "0", "Feature Price": "\u20ac6.99", "Description": "Wodka Gorbatschow", "Purchase Price": "\u20ac6.66", "Multibuy": "10"}, {"Tag": "Baustein-A", "Active To": "31.12.2015", "Shelf Price": "\u20ac2.49", "id": "117", "Campaign Type": "feature_promotion", "Active From": "15.04.2015", "Additional Info": "5x 65ml Fl./Packung, versch. Sorten", "Unit Goal": "1198", "Budget": "", "Status": "draft", "Revenue Goal": "", "Feature Price": "\u20ac1.99", "Description": "Yakult, probiotisches Getr\u00e4nk", "Purchase Price": "\u20ac1.53", "Multibuy": "10"}, {"Tag": "Baustein-A", "Active To": "31.12.2015", "Shelf Price": "\u20ac2.29", "id": "118", "Campaign Type": "feature_promotion", "Active From": "15.04.2015", "Additional Info": "Design Family, 2er Packung, 2x86 Blatt", "Unit Goal": "172", "Budget": "", "Status": "draft", "Revenue Goal": "", "Feature Price": "\u20ac1.79", "Description": "Zewa Wisch & Weg", "Purchase Price": "\u20ac1.65", "Multibuy": "10"}, {"Tag": "Baustein-D", "Active To": "31.12.2015", "Shelf Price": "\u20ac1.99", "id": "119", "Campaign Type": "feature_promotion", "Active From": "16.04.2015", "Additional Info": "200g Packung, ohne Salz, \u00f6lger\u00f6stet", "Unit Goal": "", "Budget": "", "Status": "draft", "Revenue Goal": "", "Feature Price": "", "Description": "\u00dcltje Erdn\u00fcsse", "Purchase Price": "", "Multibuy": "3"}, {"Tag": "", "Active To": "06.07.2015", "Shelf Price": "\u20ac3.29", "id": "120", "Campaign Type": "category_expansion", "Active From": "06.07.2015", "Additional Info": "200g Packung", "Unit Goal": "0", "Budget": "\u20ac0.00", "Status": "draft", "Revenue Goal": "0", "Feature Price": "\u20ac0.00", "Description": "Alpenhain Backcamembert", "Purchase Price": "\u20ac2.11", "Multibuy": "3"}, {"Tag": "", "Active To": "03.07.2015", "Shelf Price": "\u20ac1.49", "id": "121", "Campaign Type": "category_expansion", "Active From": "01.07.2015", "Additional Info": "Mango-Vanille, 400g Becher", "Unit Goal": "0", "Budget": "\u20ac0.00", "Status": "draft", "Revenue Goal": "0", "Feature Price": "\u20ac0.00", "Description": "Andechs. Bio-Joghurt", "Purchase Price": "\u20ac0.00", "Multibuy": "5"}, {"Tag": "Baustein-D", "Active To": "14.06.2015", "Shelf Price": "\u20ac1.79", "id": "122", "Campaign Type": "category_expansion", "Active From": "16.05.2015", "Additional Info": "500g Becher, natur", "Unit Goal": "", "Budget": "", "Status": "draft", "Revenue Goal": "", "Feature Price": "", "Description": "Apostels jogurti griech. Joghurt", "Purchase Price": "\u20ac1.11", "Multibuy": "5"}, {"Tag": "", "Active To": "31.12.2015", "Shelf Price": "\u20ac1.89", "id": "123", "Campaign Type": "category_expansion", "Active From": "25.05.2015", "Additional Info": "250g Packung, versch. Sorten", "Unit Goal": "", "Budget": "", "Status": "draft", "Revenue Goal": "", "Feature Price": "", "Description": "Arla Butter", "Purchase Price": "\u20ac1.47", "Multibuy": "1"}, {"Tag": "", "Active To": "31.12.2015", "Shelf Price": "\u20ac1.99", "id": "124", "Campaign Type": "category_expansion", "Active From": "25.05.2015", "Additional Info": "0,75l Flasche, versch. Sorten", "Unit Goal": "", "Budget": "", "Status": "draft", "Revenue Goal": "", "Feature Price": "", "Description": "Aventuro Frizzante Perlwein", "Purchase Price": "\u20ac1.41", "Multibuy": "1"}, {"Tag": "", "Active To": "31.12.2015", "Shelf Price": "", "id": "125", "Campaign Type": "category_expansion", "Active From": "18.05.2015", "Additional Info": "description", "Unit Goal": "", "Budget": "", "Status": "draft", "Revenue Goal": "", "Feature Price": "", "Description": "Bonta Divina", "Purchase Price": "", "Multibuy": "1"}, {"Tag": "Baustein-D", "Active To": "14.06.2015", "Shelf Price": "\u20ac1.49", "id": "126", "Campaign Type": "category_expansion", "Active From": "16.05.2015", "Additional Info": "750g Packung, versch. Sorten", "Unit Goal": "", "Budget": "", "Status": "draft", "Revenue Goal": "", "Feature Price": "", "Description": "Brotland Sandwich Toast", "Purchase Price": "\u20ac0.90", "Multibuy": "3"}, {"Tag": "Baustein-D", "Active To": "14.06.2015", "Shelf Price": "\u20ac2.99", "id": "127", "Campaign Type": "category_expansion", "Active From": "18.05.2015", "Additional Info": "Ganzes St\u00fcck", "Unit Goal": "", "Budget": "", "Status": "draft", "Revenue Goal": "", "Feature Price": "", "Description": "Cantaloupe Melone", "Purchase Price": "", "Multibuy": "3"}, {"Tag": "Baustein-D", "Active To": "31.12.2015", "Shelf Price": "", "id": "128", "Campaign Type": "category_expansion", "Active From": "25.05.2015", "Additional Info": "10 x 0,2L Trinkbeutel, versch. Sorten", "Unit Goal": "", "Budget": "", "Status": "draft", "Revenue Goal": "", "Feature Price": "", "Description": "Capri-Sonne Saft", "Purchase Price": "\u20ac0.19", "Multibuy": "5"}, {"Tag": "", "Active To": "31.12.2015", "Shelf Price": "", "id": "129", "Campaign Type": "category_expansion", "Active From": "01.04.2015", "Additional Info": "untersch. Herkunft, beliebige Menge", "Unit Goal": "", "Budget": "", "Status": "draft", "Revenue Goal": "", "Feature Price": "", "Description": "Champignons Braun", "Purchase Price": "", "Multibuy": "1"}, {"Tag": "", "Active To": "30.11.-0001", "Shelf Price": "\u20ac6.99", "id": "130", "Campaign Type": "category_expansion", "Active From": "30.11.-0001", "Additional Info": "0,75L Fl., versch. Sorten", "Unit Goal": "", "Budget": "", "Status": "draft", "Revenue Goal": "", "Feature Price": "", "Description": "Cremant de Loire Schaumwein", "Purchase Price": "\u20ac5.46", "Multibuy": "1"}, {"Tag": "", "Active To": "31.12.2015", "Shelf Price": "\u20ac0.79", "id": "131", "Campaign Type": "category_expansion", "Active From": "25.05.2015", "Additional Info": "120g Packung", "Unit Goal": "", "Budget": "", "Status": "draft", "Revenue Goal": "", "Feature Price": "", "Description": "Danone Joghurt-Mix Mars/Twix/Bounty/M&Ms", "Purchase Price": "\u20ac0.59", "Multibuy": "1"}, {"Tag": "Baustein-D", "Active To": "14.06.2015", "Shelf Price": "\u20ac2.29", "id": "132", "Campaign Type": "category_expansion", "Active From": "25.05.2015", "Additional Info": "500g Becher, versch. Sorten", "Unit Goal": "", "Budget": "", "Status": "draft", "Revenue Goal": "", "Feature Price": "", "Description": "Dr. Oetker Fruchtgr\u00fctze", "Purchase Price": "\u20ac1.48", "Multibuy": "3"}, {"Tag": "Baustein-D", "Active To": "14.06.2015", "Shelf Price": "\u20ac1.99", "id": "133", "Campaign Type": "category_expansion", "Active From": "18.05.2015", "Additional Info": "500g Becher", "Unit Goal": "", "Budget": "", "Status": "draft", "Revenue Goal": "", "Feature Price": "", "Description": "Dr. Oetker Grie\u00dfpudding natur", "Purchase Price": "", "Multibuy": "5"}, {"Tag": "", "Active To": "31.12.2015", "Shelf Price": "\u20ac1.79", "id": "134", "Campaign Type": "category_expansion", "Active From": "25.05.2015", "Additional Info": "4x125g Packung, versch. Sorten", "Unit Goal": "", "Budget": "", "Status": "draft", "Revenue Goal": "", "Feature Price": "", "Description": "Dr. Oetker Paula Pudding", "Purchase Price": "\u20ac1.17", "Multibuy": "1"}, {"Tag": "Baustein-D", "Active To": "14.06.2015", "Shelf Price": "\u20ac1.49", "id": "135", "Campaign Type": "category_expansion", "Active From": "18.05.2015", "Additional Info": "100g Schale, S\u00fcdfr\u00fcchte", "Unit Goal": "", "Budget": "", "Status": "draft", "Revenue Goal": "", "Feature Price": "", "Description": "Eat Me Physalis", "Purchase Price": "", "Multibuy": "1"}, {"Tag": "Baustein-D", "Active To": "31.12.2015", "Shelf Price": "\u20ac2.99", "id": "136", "Campaign Type": "category_expansion", "Active From": "16.04.2015", "Additional Info": "1L Fl., trocken", "Unit Goal": "", "Budget": "", "Status": "draft", "Revenue Goal": "", "Feature Price": "", "Description": "Falkenberg Riesling", "Purchase Price": "", "Multibuy": "3"}, {"Tag": "Baustein-D", "Active To": "31.12.2015", "Shelf Price": "\u20ac2.99", "id": "137", "Campaign Type": "category_expansion", "Active From": "16.04.2015", "Additional Info": "0,75L Fl., trocken, versch. Sorten", "Unit Goal": "", "Budget": "", "Status": "draft", "Revenue Goal": "", "Feature Price": "", "Description": "Falkental  Wein", "Purchase Price": "", "Multibuy": "3"}, {"Tag": "Baustein-D", "Active To": "14.06.2015", "Shelf Price": "\u20ac0.99", "id": "138", "Campaign Type": "category_expansion", "Active From": "18.05.2015", "Additional Info": "St\u00fcckware", "Unit Goal": "", "Budget": "", "Status": "draft", "Revenue Goal": "", "Feature Price": "", "Description": "Frische Auberginen", "Purchase Price": "", "Multibuy": "5"}, {"Tag": "Baustein-D", "Active To": "22.06.2015", "Shelf Price": "", "id": "139", "Campaign Type": "category_expansion", "Active From": "25.05.2015", "Additional Info": "6er Packung, Naturkind od. Von Hier", "Unit Goal": "", "Budget": "", "Status": "draft", "Revenue Goal": "", "Feature Price": "", "Description": "Frische Bio-Eier", "Purchase Price": "", "Multibuy": "3"}, {"Tag": "Baustein-D", "Active To": "14.06.2015", "Shelf Price": "", "id": "140", "Campaign Type": "category_expansion", "Active From": "18.05.2015", "Additional Info": "Wiegeware, beliebige Menge", "Unit Goal": "", "Budget": "", "Status": "draft", "Revenue Goal": "", "Feature Price": "", "Description": "Frische Erdbeeren", "Purchase Price": "", "Multibuy": "1"}, {"Tag": "Baustein-D", "Active To": "31.12.2015", "Shelf Price": "\u20ac3.29", "id": "141", "Campaign Type": "category_expansion", "Active From": "16.04.2015", "Additional Info": "1kg Beutel, Gefl\u00fcgel, Gem\u00fcse und Getreide", "Unit Goal": "", "Budget": "", "Status": "draft", "Revenue Goal": "", "Feature Price": "", "Description": "Frolic Mini Hundefutter trocken", "Purchase Price": "", "Multibuy": "5"}, {"Tag": "", "Active To": "31.12.2015", "Shelf Price": "\u20ac0.89", "id": "142", "Campaign Type": "category_expansion", "Active From": "25.05.2015", "Additional Info": "0,25l Flasche, versch. Sorten", "Unit Goal": "", "Budget": "", "Status": "draft", "Revenue Goal": "", "Feature Price": "", "Description": "Frucht-Tiger Fruchtsaft", "Purchase Price": "\u20ac0.52", "Multibuy": "1"}, {"Tag": "Baustein-D", "Active To": "31.12.2015", "Shelf Price": "\u20ac1.05", "id": "143", "Campaign Type": "category_expansion", "Active From": "25.05.2015", "Additional Info": "250g Packung, versch. Sorten", "Unit Goal": "", "Budget": "", "Status": "draft", "Revenue Goal": "", "Feature Price": "", "Description": "Golden Toast", "Purchase Price": "\u20ac0.66", "Multibuy": "3"}, {"Tag": "Baustein-D", "Active To": "21.06.2015", "Shelf Price": "\u20ac1.29", "id": "144", "Campaign Type": "category_expansion", "Active From": "25.05.2015", "Additional Info": "500g Beutel, versch. Sorten", "Unit Goal": "", "Budget": "", "Status": "draft", "Revenue Goal": "", "Feature Price": "", "Description": "Golden Toast Toastbrot", "Purchase Price": "\u20ac0.87", "Multibuy": "3"}, {"Tag": "Baustein-D", "Active To": "31.12.2015", "Shelf Price": "\u20ac0.69", "id": "145", "Campaign Type": "category_expansion", "Active From": "16.04.2015", "Additional Info": "85g Packung, versch. Sorten", "Unit Goal": "", "Budget": "", "Status": "draft", "Revenue Goal": "", "Feature Price": "", "Description": "Gourmet Perle Katzenfutter", "Purchase Price": "", "Multibuy": "10"}, {"Tag": "", "Active To": "31.12.2015", "Shelf Price": "\u20ac1.59", "id": "146", "Campaign Type": "category_expansion", "Active From": "25.05.2015", "Additional Info": "250g Butter", "Unit Goal": "", "Budget": "", "Status": "draft", "Revenue Goal": "", "Feature Price": "", "Description": "Greenfields Originale Irische Butter", "Purchase Price": "\u20ac1.27", "Multibuy": "1"}, {"Tag": "", "Active To": "31.12.2015", "Shelf Price": "\u20ac0.89", "id": "147", "Campaign Type": "category_expansion", "Active From": "25.05.2015", "Additional Info": "100g Packung, versch. Sorten", "Unit Goal": "", "Budget": "", "Status": "draft", "Revenue Goal": "", "Feature Price": "", "Description": "Gut Auburg Butter", "Purchase Price": "\u20ac0.47", "Multibuy": "1"}, {"Tag": "Baustein-D", "Active To": "31.12.2015", "Shelf Price": "\u20ac4.29", "id": "148", "Campaign Type": "category_expansion", "Active From": "16.04.2015", "Additional Info": "250g Packung", "Unit Goal": "", "Budget": "", "Status": "draft", "Revenue Goal": "", "Feature Price": "", "Description": "Guylian Meeresfr\u00fcchte Pralinen", "Purchase Price": "", "Multibuy": "3"}, {"Tag": "Baustein-D", "Active To": "31.12.2015", "Shelf Price": "\u20ac3.49", "id": "149", "Campaign Type": "category_expansion", "Active From": "25.05.2015", "Additional Info": "2x 80g/90g Glas, versch. Sorten", "Unit Goal": "", "Budget": "", "Status": "draft", "Revenue Goal": "", "Feature Price": "", "Description": "G\u00dc Dessert im Glas", "Purchase Price": "\u20ac2.30", "Multibuy": "3"}, {"Tag": "Baustein-D", "Active To": "14.06.2015", "Shelf Price": "\u20ac1.49", "id": "150", "Campaign Type": "category_expansion", "Active From": "16.05.2015", "Additional Info": "500g Packung, versch. Sorten", "Unit Goal": "", "Budget": "", "Status": "draft", "Revenue Goal": "", "Feature Price": "", "Description": "Harry B\u00e4cker-Frisch Brot", "Purchase Price": "\u20ac0.85", "Multibuy": "3"}, {"Tag": "Baustein-D", "Active To": "21.06.2015", "Shelf Price": "\u20ac1.59", "id": "151", "Campaign Type": "category_expansion", "Active From": "25.05.2015", "Additional Info": "500g Beutel, Vollkornbrot, versch. Sorten", "Unit Goal": "", "Budget": "", "Status": "draft", "Revenue Goal": "", "Feature Price": "", "Description": "Harry Das volle Korn", "Purchase Price": "\u20ac0.98", "Multibuy": "3"}, {"Tag": "Baustein-D", "Active To": "21.06.2015", "Shelf Price": "\u20ac1.29", "id": "152", "Campaign Type": "category_expansion", "Active From": "25.05.2015", "Additional Info": "500g Beutel, versch. Sorten", "Unit Goal": "", "Budget": "", "Status": "draft", "Revenue Goal": "", "Feature Price": "", "Description": "Harry Toastbrot", "Purchase Price": "\u20ac0.77", "Multibuy": "3"}, {"Tag": "Baustein-D", "Active To": "14.06.2015", "Shelf Price": "\u20ac1.89", "id": "153", "Campaign Type": "category_expansion", "Active From": "18.05.2015", "Additional Info": "500g Packung, tiefg.", "Unit Goal": "", "Budget": "", "Status": "draft", "Revenue Goal": "", "Feature Price": "", "Description": "Iglo Blattspinat mit ganzen Bl\u00e4ttern", "Purchase Price": "", "Multibuy": "3"}, {"Tag": "Baustein-D", "Active To": "31.12.2015", "Shelf Price": "\u20ac3.99", "id": "154", "Campaign Type": "category_expansion", "Active From": "16.04.2015", "Additional Info": "4kg Beutel, Gefl\u00fcgel und Rind", "Unit Goal": "", "Budget": "", "Status": "draft", "Revenue Goal": "", "Feature Price": "", "Description": "Jeden Tag Hundefutter trocken", "Purchase Price": "", "Multibuy": "10"}, {"Tag": "", "Active To": "31.12.2015", "Shelf Price": "", "id": "155", "Campaign Type": "category_expansion", "Active From": "18.05.2015", "Additional Info": "description", "Unit Goal": "", "Budget": "", "Status": "draft", "Revenue Goal": "", "Feature Price": "", "Description": "Kerrygold", "Purchase Price": "", "Multibuy": "1"}, {"Tag": "Baustein-D", "Active To": "31.12.2015", "Shelf Price": "\u20ac0.69", "id": "156", "Campaign Type": "category_expansion", "Active From": "16.04.2015", "Additional Info": "400g, Rind/Huhn in So\u00dfe", "Unit Goal": "", "Budget": "", "Status": "draft", "Revenue Goal": "", "Feature Price": "", "Description": "Kitekat Katzenfutter Dose", "Purchase Price": "", "Multibuy": "10"}, {"Tag": "Baustein-D", "Active To": "14.06.2015", "Shelf Price": "\u20ac1.49", "id": "157", "Campaign Type": "category_expansion", "Active From": "25.05.2015", "Additional Info": "500g Glas, versch. Sorten", "Unit Goal": "", "Budget": "", "Status": "draft", "Revenue Goal": "", "Feature Price": "", "Description": "Landliebe Joghurt", "Purchase Price": "\u20ac0.99", "Multibuy": "5"}, {"Tag": "Baustein-D", "Active To": "14.06.2015", "Shelf Price": "\u20ac0.39", "id": "158", "Campaign Type": "category_expansion", "Active From": "18.05.2015", "Additional Info": "St\u00fcckware", "Unit Goal": "", "Budget": "", "Status": "draft", "Revenue Goal": "", "Feature Price": "", "Description": "Limetten", "Purchase Price": "", "Multibuy": "5"}, {"Tag": "Baustein-D", "Active To": "14.06.2015", "Shelf Price": "\u20ac3.99", "id": "159", "Campaign Type": "category_expansion", "Active From": "25.05.2015", "Additional Info": "137g Packung, Vollmilchschokolade", "Unit Goal": "", "Budget": "", "Status": "draft", "Revenue Goal": "", "Feature Price": "", "Description": "Lindt Lindor Kugeln", "Purchase Price": "\u20ac2.38", "Multibuy": "1"}, {"Tag": "Baustein-D", "Active To": "14.06.2015", "Shelf Price": "\u20ac3.50", "id": "160", "Campaign Type": "category_expansion", "Active From": "16.05.2015", "Additional Info": "30g Packung", "Unit Goal": "", "Budget": "", "Status": "draft", "Revenue Goal": "", "Feature Price": "", "Description": "Lindt von Herzen Mini Pralin\u00e9s", "Purchase Price": "\u20ac2.11", "Multibuy": "1"}, {"Tag": "", "Active To": "31.12.2015", "Shelf Price": "\u20ac1.89", "id": "161", "Campaign Type": "category_expansion", "Active From": "25.05.2015", "Additional Info": "250g Butter", "Unit Goal": "", "Budget": "", "Status": "draft", "Revenue Goal": "", "Feature Price": "", "Description": "Mark Brandenburg Weidebutter", "Purchase Price": "\u20ac1.55", "Multibuy": "1"}, {"Tag": "Baustein-D", "Active To": "31.12.2015", "Shelf Price": "\u20ac3.99", "id": "162", "Campaign Type": "category_expansion", "Active From": "16.04.2015", "Additional Info": "0,75L Fl., Grau-/Weissburgunder od. Riesling", "Unit Goal": "", "Budget": "", "Status": "draft", "Revenue Goal": "", "Feature Price": "", "Description": "Maybach Wein", "Purchase Price": "", "Multibuy": "3"}, {"Tag": "", "Active To": "31.12.2015", "Shelf Price": "\u20ac1.19", "id": "163", "Campaign Type": "category_expansion", "Active From": "25.05.2015", "Additional Info": "125g Butter", "Unit Goal": "", "Budget": "", "Status": "draft", "Revenue Goal": "", "Feature Price": "", "Description": "Meggle Alpenbutter", "Purchase Price": "\u20ac0.79", "Multibuy": "1"}, {"Tag": "Baustein-D", "Active To": "14.06.2015", "Shelf Price": "\u20ac2.89", "id": "164", "Campaign Type": "category_expansion", "Active From": "16.05.2015", "Additional Info": "250g Packung, versch. Sorten", "Unit Goal": "", "Budget": "", "Status": "draft", "Revenue Goal": "", "Feature Price": "", "Description": "Merci Finest Selection", "Purchase Price": "\u20ac2.46", "Multibuy": "3"}, {"Tag": "So1 Test", "Active To": "17.05.2015", "Shelf Price": "\u20ac1.99", "id": "165", "Campaign Type": "category_expansion", "Active From": "08.05.2015", "Additional Info": "80g Schale", "Unit Goal": "100", "Budget": "", "Status": "draft", "Revenue Goal": "", "Feature Price": "", "Description": "Naturkind Bio Rucola", "Purchase Price": "\u20ac0.50", "Multibuy": "3"}, {"Tag": "", "Active To": "31.12.2015", "Shelf Price": "\u20ac2.19", "id": "166", "Campaign Type": "category_expansion", "Active From": "25.05.2015", "Additional Info": "250g Sauerrahmbutter", "Unit Goal": "", "Budget": "", "Status": "draft", "Revenue Goal": "", "Feature Price": "", "Description": "Naturkind Deutsche Bio Markenbutter", "Purchase Price": "\u20ac1.58", "Multibuy": "1"}, {"Tag": "", "Active To": "31.12.2015", "Shelf Price": "", "id": "167", "Campaign Type": "category_expansion", "Active From": "18.05.2015", "Additional Info": "description", "Unit Goal": "", "Budget": "", "Status": "draft", "Revenue Goal": "", "Feature Price": "", "Description": "Naturkind Sauerrahm Butter", "Purchase Price": "", "Multibuy": "1"}, {"Tag": "", "Active To": "31.12.2015", "Shelf Price": "\u20ac1.99", "id": "168", "Campaign Type": "category_expansion", "Active From": "25.05.2015", "Additional Info": "1l Packung, Cranberry Classic", "Unit Goal": "", "Budget": "", "Status": "draft", "Revenue Goal": "", "Feature Price": "", "Description": "Ocean Spray Fruchtsaftgetr\u00e4nk Cranberry", "Purchase Price": "\u20ac1.30", "Multibuy": "1"}, {"Tag": "Baustein-D", "Active To": "14.06.2015", "Shelf Price": "\u20ac0.99", "id": "169", "Campaign Type": "category_expansion", "Active From": "16.05.2015", "Additional Info": "500g Becher, 0,1% Fett", "Unit Goal": "", "Budget": "", "Status": "draft", "Revenue Goal": "", "Feature Price": "", "Description": "Optiwell Magermilch Joghurt", "Purchase Price": "\u20ac0.68", "Multibuy": "5"}, {"Tag": "", "Active To": "31.12.2015", "Shelf Price": "", "id": "170", "Campaign Type": "category_expansion", "Active From": "01.04.2015", "Additional Info": "Mein G\u00e4rtner, Kl. I, beliebige Menge", "Unit Goal": "", "Budget": "", "Status": "draft", "Revenue Goal": "", "Feature Price": "", "Description": "Paprika rot, gelb, orange", "Purchase Price": "", "Multibuy": "1"}, {"Tag": "Baustein-D", "Active To": "31.12.2015", "Shelf Price": "\u20ac0.99", "id": "171", "Campaign Type": "category_expansion", "Active From": "16.04.2015", "Additional Info": "300g Dose, versch. Sorten", "Unit Goal": "", "Budget": "", "Status": "draft", "Revenue Goal": "", "Feature Price": "", "Description": "Pedigree Hundefutter", "Purchase Price": "", "Multibuy": "10"}, {"Tag": "Baustein-D", "Active To": "14.06.2015", "Shelf Price": "\u20ac1.79", "id": "172", "Campaign Type": "category_expansion", "Active From": "16.05.2015", "Additional Info": "1L Packung, versch. Sorten", "Unit Goal": "", "Budget": "", "Status": "draft", "Revenue Goal": "", "Feature Price": "", "Description": "Pfanner Fairtrade Fruchts\u00e4fte", "Purchase Price": "\u20ac1.21", "Multibuy": "5"}, {"Tag": "", "Active To": "31.12.2015", "Shelf Price": "\u20ac2.59", "id": "173", "Campaign Type": "category_expansion", "Active From": "25.05.2015", "Additional Info": "250g Packung", "Unit Goal": "", "Budget": "", "Status": "draft", "Revenue Goal": "", "Feature Price": "", "Description": "President Meersalz Butter", "Purchase Price": "\u20ac1.96", "Multibuy": "1"}, {"Tag": "Baustein-D", "Active To": "31.12.2015", "Shelf Price": "\u20ac4.29", "id": "174", "Campaign Type": "category_expansion", "Active From": "16.04.2015", "Additional Info": "800g Packung, versch. Sorten", "Unit Goal": "", "Budget": "", "Status": "draft", "Revenue Goal": "", "Feature Price": "", "Description": "Purina One Katzenfutter", "Purchase Price": "", "Multibuy": "10"}, {"Tag": "", "Active To": "31.12.2015", "Shelf Price": "", "id": "175", "Campaign Type": "category_expansion", "Active From": "01.04.2015", "Additional Info": "Mein G\u00e4rtner, 300g Schale", "Unit Goal": "", "Budget": "", "Status": "draft", "Revenue Goal": "", "Feature Price": "", "Description": "Rispen-Tomaten", "Purchase Price": "", "Multibuy": "1"}, {"Tag": "Baustein-D", "Active To": "31.12.2015", "Shelf Price": "\u20ac2.29", "id": "176", "Campaign Type": "category_expansion", "Active From": "25.05.2015", "Additional Info": "0,75L Fl., versch. Sorten", "Unit Goal": "", "Budget": "", "Status": "draft", "Revenue Goal": "", "Feature Price": "", "Description": "Rotk\u00e4ppchen Sekt o. Fruchtsecco", "Purchase Price": "", "Multibuy": "3"}, {"Tag": "Baustein-D", "Active To": "14.06.2015", "Shelf Price": "\u20ac0.99", "id": "177", "Campaign Type": "category_expansion", "Active From": "16.05.2015", "Additional Info": "400g Becher, 3,5% Fett", "Unit Goal": "", "Budget": "", "Status": "draft", "Revenue Goal": "", "Feature Price": "", "Description": "Schwarzwaldmilch laktosefreier Joghurt", "Purchase Price": "\u20ac0.69", "Multibuy": "5"}, {"Tag": "Baustein-D", "Active To": "31.12.2015", "Shelf Price": "\u20ac0.99", "id": "178", "Campaign Type": "category_expansion", "Active From": "16.04.2015", "Additional Info": "80g Schale, versch. Sorten", "Unit Goal": "", "Budget": "", "Status": "draft", "Revenue Goal": "", "Feature Price": "", "Description": "Sheba Katzenfutter", "Purchase Price": "", "Multibuy": "10"}, {"Tag": "Baustein-D", "Active To": "14.06.2015", "Shelf Price": "\u20ac1.99", "id": "179", "Campaign Type": "category_expansion", "Active From": "18.05.2015", "Additional Info": "Wiegeware", "Unit Goal": "", "Budget": "", "Status": "draft", "Revenue Goal": "", "Feature Price": "", "Description": "Star Marke Bananen", "Purchase Price": "", "Multibuy": "1"}, {"Tag": "", "Active To": "31.12.2015", "Shelf Price": "\u20ac1.49", "id": "180", "Campaign Type": "category_expansion", "Active From": "25.05.2015", "Additional Info": "6x55g Packung", "Unit Goal": "", "Budget": "", "Status": "draft", "Revenue Goal": "", "Feature Price": "", "Description": "Zott Monte Dessert weniger S\u00fc\u00df", "Purchase Price": "\u20ac1.07", "Multibuy": "1"}, {"Tag": "", "Active To": "31.12.2015", "Shelf Price": "\u20ac1.79", "id": "181", "Campaign Type": "category_expansion", "Active From": "25.05.2015", "Additional Info": "4x100g Packung", "Unit Goal": "", "Budget": "", "Status": "draft", "Revenue Goal": "", "Feature Price": "", "Description": "Zott Monte Maxi dessert", "Purchase Price": "\u20ac1.17", "Multibuy": "1"}, {"Tag": "", "Active To": "31.12.2015", "Shelf Price": "\u20ac1.69", "id": "182", "Campaign Type": "category_expansion", "Active From": "25.05.2015", "Additional Info": "2x75g Packung, Classico mit Amaretto", "Unit Goal": "", "Budget": "", "Status": "draft", "Revenue Goal": "", "Feature Price": "", "Description": "Zott Tiramisu Doppelpack", "Purchase Price": "\u20ac1.09", "Multibuy": "1"}, {"Tag": "Baustein-D", "Active To": "14.06.2015", "Shelf Price": "\u20ac1.99", "id": "183", "Campaign Type": "category_expansion", "Active From": "18.05.2015", "Additional Info": "2er Packung, frisches Gem\u00fcse", "Unit Goal": "", "Budget": "", "Status": "draft", "Revenue Goal": "", "Feature Price": "", "Description": "Zuckermais", "Purchase Price": "", "Multibuy": "3"}, {"Tag": "", "Active To": "31.12.2015", "Shelf Price": "\u20ac1.65", "id": "184", "Campaign Type": "brand_switching", "Active From": "12.03.2015", "Additional Info": "PET-Flasche, versch. Sorten", "Unit Goal": "15000", "Budget": "", "Status": "draft", "Revenue Goal": "", "Feature Price": "\u20ac1.19", "Description": "Coca-Cola 2L", "Purchase Price": "\u20ac1.05", "Multibuy": "5"}, {"Tag": "", "Active To": "31.12.2015", "Shelf Price": "", "id": "185", "Campaign Type": "brand_switching", "Active From": "12.03.2015", "Additional Info": "beliebige Menge, St\u00fcckware", "Unit Goal": "", "Budget": "", "Status": "draft", "Revenue Goal": "", "Feature Price": "", "Description": "Frische Mango", "Purchase Price": "", "Multibuy": "1"}, {"Tag": "", "Active To": "31.12.2015", "Shelf Price": "", "id": "186", "Campaign Type": "brand_switching", "Active From": "12.03.2015", "Additional Info": "Mein G\u00e4rtner, 300g Schale", "Unit Goal": "", "Budget": "", "Status": "draft", "Revenue Goal": "", "Feature Price": "", "Description": "Rispen-Tomaten", "Purchase Price": "", "Multibuy": "1"}, {"Tag": "", "Active To": "31.12.2015", "Shelf Price": "\u20ac2.19", "id": "187", "Campaign Type": "brand_switching", "Active From": "12.03.2015", "Additional Info": "270-340g, versch. Sorten", "Unit Goal": "5000", "Budget": "", "Status": "draft", "Revenue Goal": "", "Feature Price": "\u20ac1.39", "Description": "Schwartau Marmeladen", "Purchase Price": "", "Multibuy": "5"}]